{
  "number": "293",
  "title": "FIVORIANA MASINA",
  "verses": {
    "1": "Avia Fanahy Masina ô,\nTariho izao fivoriana izao\nFenoy hery avy Aminao\nIzahay rehetra tong'eto izao.",
    "2": "Jesosy Andriamanitra ô!\nIndro vory ny mpanomponao,\nHidera ary hisaotra Anao,\nKa mijoroa eto anilanay.",
    "3": "Hianao izay tafangon'eto\nMba omeo ny Tompo ny fonao\nKa hamasino ny fiainanao\nFa manatrika eto Izy izao.",
    "4": "Ry Tompo, hamasinonao\nSy anjakao ny fiangonanao\nFa Jesosy no famonjena,\nFah' marinana mandrakizay"
  }
}