{
  "number": "801",
  "title": "FANAMASINAN-TENA",
  "verses": {
    "1": "Manolo-tena ho Anao ry Ray\nNamabo ahy ny fitiavanao\nFoiko ho Anao ny fiainako manontolo\nSy izay rehetra momba ahy",
    "2": "Inona koa no azoko omena\nAnao ny lanitra sy ny tany\nNy foko izay mitia sy midera Anao\nAmbony noho ny volamena",
    "3": "Tiako ny Tompo malemy fanahy\nNy manaraka Anao tsy an-tery\nManaiky izay baikonao rehetra\nNo fifaliako mandrakizay",
    "4": "Ho an'izao tontolo izao mahantra\nSatria nandà ny fiadananao\nEkeo Kristy, Ianao feno antra\n'Zao fo maniry ireo ho Anao."
  }
}